structio/__init__.py
structio/abc.py
structio/exceptions.py
structio/parallel.py
structio/path.py
structio/sync.py
structio/thread.py
structio/core/__init__.py
structio/core/context.py
structio/core/run.py
structio/core/syscalls.py
structio/core/task.py
structio/core/tooling.py
structio/core/kernels/__init__.py
structio/core/kernels/fifo.py
structio/core/managers/__init__.py
structio/core/managers/io/__init__.py
structio/core/managers/io/simple.py
structio/core/managers/signals/__init__.py
structio/core/managers/signals/sigint.py
structio/core/time/__init__.py
structio/core/time/clock.py
structio/core/time/queue.py
structio/io/__init__.py
structio/io/files.py
structio/io/socket.py
structio/util/__init__.py
structio/util/ki.py
structio/util/misc.py
structured_io-0.1.0.dist-info/LICENSE
structured_io-0.1.0.dist-info/METADATA
structured_io-0.1.0.dist-info/WHEEL
structured_io-0.1.0.dist-info/top_level.txt
structured_io-0.1.0.dist-info/RECORD
