Metadata-Version: 2.1
Name: structured-io
Version: 0.1.0
Summary: An experimental structured concurrency framework
Home-page: https://example.com
Author: nocturn9x
Author-email: nocturn9x@nocturn9x.space
Classifier: Programming Language :: Python :: 3
Classifier: Operating System :: OS Independent
Classifier: License :: OSI Approved :: Apache Software License
Requires-Python: >=3.8
License-File: LICENSE
